{"version":3,"kind":"Article","sha256":"bf8b68a428236fa4d8ac819bf2ea4996c7542b2be92ffb1cc921f88f38d19d58","slug":"index","location":"/intro.md","dependencies":[],"frontmatter":{"title":"STAI-TUNED: ScienTific Artificial Intelligence TUtorials for tunNEl Design","content_includes_title":false,"authors":[{"id":"Alec Tristani","name":"Alec Tristani"}],"license":{"content":{"id":"CC-BY-4.0","url":"https://creativecommons.org/licenses/by/4.0/","name":"Creative Commons Attribution 4.0 International","free":true,"CC":true}},"thumbnail":"/04a4c4a42d6d848686104ba5f4a0022b.png","exports":[{"format":"md","filename":"intro.md","url":"/intro-1dd426344b98f3e5c7354abf76650843.md"}]},"mdast":{"type":"root","children":[{"type":"block","children":[{"type":"container","kind":"quote","children":[{"type":"blockquote","children":[{"type":"paragraph","position":{"start":{"line":5,"column":1},"end":{"line":5,"column":1}},"children":[{"type":"text","value":"You see, in this world, there’s two kinds of people, my friend: those with loaded guns, and those who dig.","position":{"start":{"line":5,"column":1},"end":{"line":5,"column":1}},"key":"mkJfgNYg15"}],"key":"EGixqfG3kP"}],"key":"uke8tSkXGZ"},{"type":"caption","children":[{"type":"paragraph","position":{"start":{"line":7,"column":1},"end":{"line":7,"column":1}},"children":[{"type":"emphasis","position":{"start":{"line":7,"column":1},"end":{"line":7,"column":1}},"children":[{"type":"text","value":"The Good, the Bad and the Ugly (1966)","position":{"start":{"line":7,"column":1},"end":{"line":7,"column":1}},"key":"T1mrlzX7nm"}],"key":"YoaaqXl6sC"}],"key":"KVmZZu7LGW"}],"key":"vRyAsNjOXt"}],"class":"epigraph","key":"qVuJBiyO4O"},{"type":"paragraph","position":{"start":{"line":10,"column":1},"end":{"line":10,"column":1}},"children":[{"type":"text","value":"Welcome! This book proposes numerical tools with python implementation for simulating underground constructions, such as tunnels.","position":{"start":{"line":10,"column":1},"end":{"line":10,"column":1}},"key":"fb2VCMtcZw"}],"key":"sJsIiZxo5x"},{"type":"heading","depth":2,"position":{"start":{"line":13,"column":1},"end":{"line":13,"column":1}},"children":[{"type":"text","value":"Tutorials","position":{"start":{"line":13,"column":1},"end":{"line":13,"column":1}},"key":"v1bUx6CNYF"}],"identifier":"tutorials","label":"Tutorials","html_id":"tutorials","implicit":true,"key":"wj9pU4SlMd"},{"type":"paragraph","position":{"start":{"line":15,"column":1},"end":{"line":15,"column":1}},"children":[{"type":"text","value":"This section will introduce you to the implementation of machine learning surrogate models using ","position":{"start":{"line":15,"column":1},"end":{"line":15,"column":1}},"key":"AaNvgnIeVO"},{"type":"link","url":"https://docs.jax.dev/en/latest/index.html","position":{"start":{"line":15,"column":1},"end":{"line":15,"column":1}},"children":[{"type":"text","value":"JAX","position":{"start":{"line":15,"column":1},"end":{"line":15,"column":1}},"key":"yCND9HI8Yv"}],"urlSource":"https://docs.jax.dev/en/latest/index.html","key":"AHaLwlKSZ0"},{"type":"text","value":" and the creation of synthetic datasets using ","position":{"start":{"line":15,"column":1},"end":{"line":15,"column":1}},"key":"JYQAM6J7oL"},{"type":"link","url":"http://fenicsproject.org","position":{"start":{"line":15,"column":1},"end":{"line":15,"column":1}},"children":[{"type":"text","value":"FEniCSx","position":{"start":{"line":15,"column":1},"end":{"line":15,"column":1}},"key":"v65BwzmkhW"}],"urlSource":"http://fenicsproject.org","key":"RxM5s18mvv"},{"type":"text","value":".","position":{"start":{"line":15,"column":1},"end":{"line":15,"column":1}},"key":"JCA5mpeRNj"}],"key":"o3miDDdhLx"},{"type":"list","ordered":false,"spread":false,"position":{"start":{"line":17,"column":1},"end":{"line":20,"column":1}},"children":[{"type":"listItem","spread":true,"position":{"start":{"line":17,"column":1},"end":{"line":17,"column":1}},"children":[{"type":"paragraph","children":[{"type":"strong","position":{"start":{"line":17,"column":1},"end":{"line":17,"column":1}},"children":[{"type":"text","value":"Notebook 1","position":{"start":{"line":17,"column":1},"end":{"line":17,"column":1}},"key":"ZnxyvNE86B"}],"key":"z6nM52Z9bb"},{"type":"text","value":" – Multi-layer perceptron from scratch","position":{"start":{"line":17,"column":1},"end":{"line":17,"column":1}},"key":"lLzjZakBlM"}],"key":"MbcuKNLWQi"}],"key":"zRbXjmvn3w"},{"type":"listItem","spread":true,"position":{"start":{"line":18,"column":1},"end":{"line":20,"column":1}},"children":[{"type":"paragraph","children":[{"type":"strong","position":{"start":{"line":18,"column":1},"end":{"line":18,"column":1}},"children":[{"type":"text","value":"Notebook 2","position":{"start":{"line":18,"column":1},"end":{"line":18,"column":1}},"key":"xHWLJK2ZEF"}],"key":"Decjc9aTWo"},{"type":"text","value":" – Shallow tunnel surrogate modeling with FEniCSx and JAX+Equinox","position":{"start":{"line":18,"column":1},"end":{"line":18,"column":1}},"key":"DM0A1rV2P6"}],"key":"xJHgtgiFd0"}],"key":"ruHEP5aH8i"}],"key":"MOeiP2qWB3"},{"type":"paragraph","position":{"start":{"line":21,"column":1},"end":{"line":21,"column":1}},"children":[{"type":"text","value":"This work is licensed under a ","position":{"start":{"line":21,"column":1},"end":{"line":21,"column":1}},"key":"VPCNF3cNmn"},{"type":"link","url":"https://creativecommons.org/licenses/by/4.0/","position":{"start":{"line":21,"column":1},"end":{"line":21,"column":1}},"children":[{"type":"text","value":"Creative Commons Attribution 4.0 International License","position":{"start":{"line":21,"column":1},"end":{"line":21,"column":1}},"key":"Q7fQTirBNM"}],"urlSource":"https://creativecommons.org/licenses/by/4.0/","key":"mCq1PGqQG6"},{"type":"text","value":".","position":{"start":{"line":21,"column":1},"end":{"line":21,"column":1}},"key":"OjR9XNzBCy"}],"key":"LXLJhA81Vw"},{"type":"paragraph","position":{"start":{"line":23,"column":1},"end":{"line":23,"column":1}},"children":[{"type":"link","url":"https://creativecommons.org/licenses/by/4.0/","position":{"start":{"line":23,"column":1},"end":{"line":23,"column":1}},"children":[{"type":"image","url":"/04a4c4a42d6d848686104ba5f4a0022b.png","alt":"CC BY 4.0","position":{"start":{"line":23,"column":1},"end":{"line":23,"column":1}},"key":"jgAPqUfAGP","urlSource":"https://licensebuttons.net/l/by/4.0/88x31.png"}],"urlSource":"https://creativecommons.org/licenses/by/4.0/","key":"vprXLSX7da"}],"key":"vkV12hQeGt"},{"type":"heading","depth":2,"position":{"start":{"line":26,"column":1},"end":{"line":26,"column":1}},"children":[{"type":"text","value":"About the author","position":{"start":{"line":26,"column":1},"end":{"line":26,"column":1}},"key":"fYGjCSLjkN"}],"identifier":"about-the-author","label":"About the author","html_id":"about-the-author","implicit":true,"key":"fDU0lsvlmb"},{"type":"paragraph","position":{"start":{"line":28,"column":1},"end":{"line":31,"column":1}},"children":[{"type":"text","value":"Alec Tristani is currently a postdoc at Cornell University.\n","position":{"start":{"line":28,"column":1},"end":{"line":28,"column":1}},"key":"PZbKkj7RAo"},{"type":"link","url":"https://alec-yt.github.io/","position":{"start":{"line":28,"column":1},"end":{"line":28,"column":1}},"children":[{"type":"text","value":"Website","position":{"start":{"line":28,"column":1},"end":{"line":28,"column":1}},"key":"WkYupeGNqq"}],"urlSource":"https://alec-yt.github.io/","key":"kgLKn6PU79"},{"type":"text","value":"\n","position":{"start":{"line":28,"column":1},"end":{"line":28,"column":1}},"key":"d3ONTAJrEZ"},{"type":"link","url":"https://github.com/Alec-YT","position":{"start":{"line":28,"column":1},"end":{"line":28,"column":1}},"children":[{"type":"text","value":"GitHub","position":{"start":{"line":28,"column":1},"end":{"line":28,"column":1}},"key":"vYYWmn7TQB"}],"urlSource":"https://github.com/Alec-YT","error":true,"key":"UM2PpLrUaq"},{"type":"text","value":"\n","position":{"start":{"line":28,"column":1},"end":{"line":28,"column":1}},"key":"iMYMx5AFw3"},{"type":"link","url":"https://scholar.google.com/citations?user=9suyJrytUEIC&hl=en","position":{"start":{"line":28,"column":1},"end":{"line":28,"column":1}},"children":[{"type":"text","value":"Scholar","position":{"start":{"line":28,"column":1},"end":{"line":28,"column":1}},"key":"pBfybU6JVQ"}],"urlSource":"https://scholar.google.com/citations?user=9suyJrytUEIC&hl=en","key":"mvDl5LSQE9"}],"key":"Vau8FHUdPy"}],"key":"cETr2kM0Cp"}],"key":"z1yKmAzfhf"},"references":{"cite":{"order":[],"data":{}}}}